MANIFEST.in
README.rst
setup.py
django_template_email.egg-info/PKG-INFO
django_template_email.egg-info/SOURCES.txt
django_template_email.egg-info/dependency_links.txt
django_template_email.egg-info/top_level.txt
template_email/__init__.py
template_email/models.py
template_email/templatetags/__init__.py
template_email/templatetags/email.py