Metadata-Version: 1.1
Name: django-template-email
Version: 0.1
Summary: A useful tool for building email messages using django templates
Home-page: http://github.com/bendavis78/django-template-email
Author: Ben Davis
Author-email: code@bendavismedia
License: UNKNOWN
Keywords: savid
Platform: UNKNOWN
Classifier: Development Status :: 4 - Beta
Classifier: Intended Audience :: Developers
Classifier: Operating System :: OS Independent
Classifier: Programming Language :: Python
Classifier: Topic :: Software Development :: Libraries :: Python Modules
